drf_verbose_serializers/__init__.py
drf_verbose_serializers/verbose_serializers.py
drf_verbose_serializers-0.1.0.dist-info/licenses/LICENSE
drf_verbose_serializers-0.1.0.dist-info/METADATA
drf_verbose_serializers-0.1.0.dist-info/WHEEL
drf_verbose_serializers-0.1.0.dist-info/top_level.txt
drf_verbose_serializers-0.1.0.dist-info/RECORD
